pytools_command/__init__.py
pytools_command/core.py
pytools_command-0.9.0.dist-info/DESCRIPTION.rst
pytools_command-0.9.0.dist-info/METADATA
pytools_command-0.9.0.dist-info/RECORD
pytools_command-0.9.0.dist-info/WHEEL
pytools_command-0.9.0.dist-info/metadata.json
pytools_command-0.9.0.dist-info/top_level.txt
