Metadata-Version: 2.0
Name: pytools-command
Version: 0.9.0
Summary: A collection of functions to run and evaluate external commands from Python.
Home-page: https://github.com/pytools/pytools-command
Author: Richard King
Author-email: richrdkng@gmail.com
License: MIT
Keywords: command exec observe pytools development
Platform: UNKNOWN
Classifier: Development Status :: 4 - Beta
Classifier: Intended Audience :: Developers
Classifier: Topic :: Software Development
Classifier: License :: OSI Approved :: MIT License
Classifier: Programming Language :: Python :: 2
Classifier: Programming Language :: Python :: 2.7
Classifier: Programming Language :: Python :: 3
Classifier: Programming Language :: Python :: 3.3
Classifier: Programming Language :: Python :: 3.4
Classifier: Programming Language :: Python :: 3.5
